odoo10_addon_auth_api_key-10.0.1.0.1-nspkg.pth
odoo/addons/auth_api_key/README.rst
odoo/addons/auth_api_key/__init__.py
odoo/addons/auth_api_key/__manifest__.py
odoo/addons/auth_api_key/i18n/auth_api_key.pot
odoo/addons/auth_api_key/models/__init__.py
odoo/addons/auth_api_key/models/auth_api_key.py
odoo/addons/auth_api_key/models/ir_http.py
odoo/addons/auth_api_key/readme/CONFIGURE.rst
odoo/addons/auth_api_key/readme/CONTRIBUTORS.rst
odoo/addons/auth_api_key/readme/DESCRIPTION.rst
odoo/addons/auth_api_key/readme/USAGE.rst
odoo/addons/auth_api_key/static/description/index.html
odoo/addons/auth_api_key/tests/__init__.py
odoo/addons/auth_api_key/tests/test_auth_api_key.py
odoo10_addon_auth_api_key-10.0.1.0.1.dist-info/METADATA
odoo10_addon_auth_api_key-10.0.1.0.1.dist-info/WHEEL
odoo10_addon_auth_api_key-10.0.1.0.1.dist-info/namespace_packages.txt
odoo10_addon_auth_api_key-10.0.1.0.1.dist-info/top_level.txt
odoo10_addon_auth_api_key-10.0.1.0.1.dist-info/RECORD
